sand/__init__.py
sand/__version__.py
sand/csv.py
sand/degree.py
sand/graph.py
sand/groups.py
sand/matrix.py
sand/modularity.py
sand/time.py
sand/cytoscape/__init__.py
sand/cytoscape/app.py
sand/cytoscape/positions.py
sand/cytoscape/themes/__init__.py
sand/cytoscape/themes/colors.py
sand/cytoscape/themes/label_positions.py
sand/cytoscape/themes/ops.py
sand-0.2.1.dist-info/LICENSE.txt
sand-0.2.1.dist-info/METADATA
sand-0.2.1.dist-info/NOTICE.txt
sand-0.2.1.dist-info/WHEEL
sand-0.2.1.dist-info/top_level.txt
sand-0.2.1.dist-info/RECORD
