Metadata-Version: 2.1
Name: sand
Version: 0.2.1
Summary: SAND: System Architecture as a Network of Dependencies
Home-page: https://github.com/testedminds/sand
Author: Bobby Norton
Author-email: bobby@testedminds.com
License: Apache License 2.0
Keywords: Architecture,Network,Graph
Platform: UNKNOWN
Classifier: Development Status :: 4 - Beta
Classifier: Intended Audience :: Developers
Classifier: Intended Audience :: Science/Research
Classifier: Intended Audience :: System Administrators
Classifier: Topic :: Scientific/Engineering
Classifier: Topic :: Utilities
Classifier: Environment :: Console
Classifier: Operating System :: MacOS :: MacOS X
Classifier: Operating System :: POSIX
Classifier: License :: OSI Approved :: Apache Software License
Classifier: Programming Language :: Python :: 3
Classifier: Programming Language :: Python :: 3 :: Only
Classifier: Programming Language :: Python :: 3.4
Classifier: Programming Language :: Python :: 3.5
Classifier: Programming Language :: Python :: 3.6
Classifier: Programming Language :: Python :: 3.7
Classifier: Programming Language :: Python :: 3.8
Classifier: Programming Language :: Python :: 3.9
Requires-Dist: bokeh (<3.0,>=2.0)
Requires-Dist: cairocffi (<2.0,>=1.0)
Requires-Dist: pandas (<2.0,>1.1)
Requires-Dist: py2cytoscape (<1.0,>=0.7.1)
Requires-Dist: python-igraph (<1.0,>=0.8.3)
